{
    "Ar36": {
        "error": 0.00038605949805835976,
        "error_type": "",
        "fit": "previous",
        "references": [
            {
                "exclude": false,
                "record_id": "ba-01-A-32061"
            }
        ],
        "value": 0.025913998565038603
    },
    "Ar37": {
        "error": 0.00900265542622554,
        "error_type": "",
        "fit": "previous",
        "references": [
            {
                "exclude": false,
                "record_id": "ba-01-A-32061"
            }
        ],
        "value": 0.02320810318953424
    },
    "Ar38": {
        "error": 0.010887046958093304,
        "error_type": "",
        "fit": "previous",
        "references": [
            {
                "exclude": false,
                "record_id": "ba-01-A-32061"
            }
        ],
        "value": 0.030721595797204355
    },
    "Ar39": {
        "error": 0.008945809270126566,
        "error_type": "",
        "fit": "previous",
        "references": [
            {
                "exclude": false,
                "record_id": "ba-01-A-32061"
            }
        ],
        "value": 0.04885849234938445
    },
    "Ar40": {
        "error": 0.02261813725012664,
        "error_type": "",
        "fit": "previous",
        "references": [
            {
                "exclude": false,
                "record_id": "ba-01-A-32061"
            }
        ],
        "value": 7.539842545271406
    }
}