{
    "Ar36": {
        "error": 0.0003221650140714449,
        "error_type": "",
        "fit": "previous",
        "references": [
            {
                "exclude": false,
                "record_id": "ba-01-A-31965"
            }
        ],
        "value": 0.020477998037789696
    },
    "Ar37": {
        "error": 0.00930676371062916,
        "error_type": "",
        "fit": "previous",
        "references": [
            {
                "exclude": false,
                "record_id": "ba-01-A-31965"
            }
        ],
        "value": 0.04363388103663729
    },
    "Ar38": {
        "error": 0.011420446891554793,
        "error_type": "",
        "fit": "previous",
        "references": [
            {
                "exclude": false,
                "record_id": "ba-01-A-31965"
            }
        ],
        "value": 0.02363475650929504
    },
    "Ar39": {
        "error": 0.008877532376743309,
        "error_type": "",
        "fit": "previous",
        "references": [
            {
                "exclude": false,
                "record_id": "ba-01-A-31965"
            }
        ],
        "value": 0.025911253072158403
    },
    "Ar40": {
        "error": 0.021020950324153114,
        "error_type": "",
        "fit": "previous",
        "references": [
            {
                "exclude": false,
                "record_id": "ba-01-A-31965"
            }
        ],
        "value": 5.656056211407067
    }
}